{
  "colores": [
    {
      "nombreColor": "Blanco",
      "codigoColor": "#ffffff",
      "id": "0761"
    },
    {
      "nombreColor": "Crema 2",
      "codigoColor": "#fee0ff",
      "id": "33c5"
    },
    {
      "nombreColor": "Crema ",
      "codigoColor": "#fee0ff",
      "id": "1e8c"
    },
    {
      "nombreColor": "blanco 2",
      "codigoColor": "#ffffff",
      "id": "a189"
    },
    {
      "nombreColor": "Verde claro",
      "codigoColor": "#00d604",
      "id": "37d9"
    },
    {
      "nombreColor": "Celeste",
      "codigoColor": "#33beff",
      "id": "fe68"
    }
  ]
}